MANIFEST.in
README.md
UNLICENSE
setup.py
staples.py
Staples.egg-info/PKG-INFO
Staples.egg-info/SOURCES.txt
Staples.egg-info/dependency_links.txt
Staples.egg-info/entry_points.txt
Staples.egg-info/top_level.txt